opinecli/__init__.py
opinecli/auth.py
opinecli/cli.py
opinecli/config.py
opinecli/data.py
opinecli/init.py
opinecli/organization.py
opinecli/project.py
opinecli/subscription.py
opinecli/system.py
opinecli/user.py
opine_cli-0.2.1.dist-info/METADATA
opine_cli-0.2.1.dist-info/WHEEL
opine_cli-0.2.1.dist-info/entry_points.txt
opine_cli-0.2.1.dist-info/top_level.txt
opine_cli-0.2.1.dist-info/RECORD
