Metadata-Version: 2.1
Name: opine-cli
Version: 0.2.1
Summary: A command line interface for Opine
Home-page: https://www.opine.world
Author: Opine @ Cognate Systems
Author-email: info@opine.world
License: UNKNOWN
Project-URL: Bug Tracker, https://www.opine.world
Platform: UNKNOWN
Classifier: Programming Language :: Python :: 3.6
Classifier: License :: OSI Approved :: MIT License
Classifier: Operating System :: OS Independent
Requires-Python: >=3.6
Requires-Dist: pandas
Requires-Dist: fire
Requires-Dist: tabulate
Requires-Dist: colorama
